sentle/__init__.py
sentle/cloud_mask.py
sentle/const.py
sentle/nbar.py
sentle/reproject_util.py
sentle/sentinel1.py
sentle/sentinel2.py
sentle/sentle.py
sentle/snow_mask.py
sentle/stac.py
sentle/utils.py
sentle/data/cloudmodel.pt
sentle/data/sentinel2_grid_stripped_with_epsg.gpkg
sentle-2025.12.1.dist-info/licenses/LICENSE.md
sentle-2025.12.1.dist-info/METADATA
sentle-2025.12.1.dist-info/WHEEL
sentle-2025.12.1.dist-info/top_level.txt
sentle-2025.12.1.dist-info/RECORD
