Metadata-Version: 2.4
Name: sentle
Version: 2025.12.1
Summary: Sentinel-1 and Sentinel-2 scalable downloader.
Author: Clemens Mosig
Author-email: clemens.mosig@uni-leipzig.de
Classifier: Development Status :: 3 - Alpha
Classifier: Intended Audience :: Education
Classifier: Programming Language :: Python :: 2
Classifier: Programming Language :: Python :: 3
Classifier: Operating System :: MacOS :: MacOS X
Classifier: Operating System :: Microsoft :: Windows
License-File: LICENSE.md
Requires-Dist: pystac-client>=0.7.7
Requires-Dist: pystac>=1.10.1
Requires-Dist: rasterio>=1.3.10
Requires-Dist: affine>=2.4.0
Requires-Dist: pandas>=2.2.2
Requires-Dist: numpy>=1.26.4
Requires-Dist: shapely>=2.0.4
Requires-Dist: zarr>3
Requires-Dist: geopandas>=0.14.4
Requires-Dist: planetary_computer>=1.0.0
Requires-Dist: scipy>=1.13.0
Requires-Dist: torch>=2.3.0
Requires-Dist: joblib>=1.4.2
Requires-Dist: tqdm>=4.66.4
Requires-Dist: sen2nbar>=2024.6.0
Requires-Dist: xarray>=2025.3.1
Requires-Dist: filelock>=3.0.0
Dynamic: author
Dynamic: author-email
Dynamic: classifier
Dynamic: description
Dynamic: license-file
Dynamic: requires-dist
Dynamic: summary
